domain_extract.py
Domain_Extract-1.0.7.dist-info/LICENSE
Domain_Extract-1.0.7.dist-info/METADATA
Domain_Extract-1.0.7.dist-info/WHEEL
Domain_Extract-1.0.7.dist-info/top_level.txt
Domain_Extract-1.0.7.dist-info/RECORD
